odetam/__init__.py
odetam/async_model.py
odetam/exceptions.py
odetam/field.py
odetam/model.py
odetam/query.py
odetam-1.5.2.dist-info/LICENSE
odetam-1.5.2.dist-info/METADATA
odetam-1.5.2.dist-info/WHEEL
odetam-1.5.2.dist-info/RECORD
