Metadata-Version: 2.1
Name: odetam
Version: 1.5.2
Summary: A simple ODM (Object Document Mapper) for Deta Base, based on pydantic.
Home-page: https://github.com/rickh94/odetam
Author: Rick Henry
Author-email: rickhenry@rickhenry.dev
Requires-Python: >=3.7,<4.0
Classifier: Programming Language :: Python :: 3
Classifier: Programming Language :: Python :: 3.7
Classifier: Programming Language :: Python :: 3.8
Classifier: Programming Language :: Python :: 3.9
Classifier: Programming Language :: Python :: 3.10
Classifier: Programming Language :: Python :: 3.11
Requires-Dist: deta[async] (>=1.1.0a2,<2.0.0)
Requires-Dist: pydantic (>=1.7,<2.0)
Requires-Dist: typing-extensions (>=4.5.0,<5.0.0)
Requires-Dist: ujson (>=4.0,<5.0)
Project-URL: Repository, https://github.com/rickh94/odetam
